xlviews/__init__.py
xlviews/chart/__init__.py
xlviews/chart/axes.py
xlviews/chart/series.py
xlviews/chart/style.py
xlviews/colors.py
xlviews/config.py
xlviews/core/__init__.py
xlviews/core/address.py
xlviews/core/formula.py
xlviews/core/index.py
xlviews/core/range.py
xlviews/core/range_collection.py
xlviews/dataframes/__init__.py
xlviews/dataframes/colorbar.py
xlviews/dataframes/dist_frame.py
xlviews/dataframes/groupby.py
xlviews/dataframes/heat_frame.py
xlviews/dataframes/sheet_frame.py
xlviews/dataframes/stats_frame.py
xlviews/dataframes/style.py
xlviews/dataframes/table.py
xlviews/figure/__init__.py
xlviews/figure/grid.py
xlviews/figure/palette.py
xlviews/figure/plot.py
xlviews/py.typed
xlviews/style.py
xlviews/testing/__init__.py
xlviews/testing/chart.py
xlviews/testing/colorbar.py
xlviews/testing/common.py
xlviews/testing/dist_frame.py
xlviews/testing/figure/__init__.py
xlviews/testing/figure/facet.py
xlviews/testing/figure/plot.py
xlviews/testing/heat_frame/__init__.py
xlviews/testing/heat_frame/agg.py
xlviews/testing/heat_frame/base.py
xlviews/testing/heat_frame/common.py
xlviews/testing/heat_frame/facet.py
xlviews/testing/heat_frame/facet_agg.py
xlviews/testing/heat_frame/pair.py
xlviews/testing/sheet_frame/__init__.py
xlviews/testing/sheet_frame/base.py
xlviews/testing/sheet_frame/melt.py
xlviews/testing/sheet_frame/pivot.py
xlviews/testing/stats_frame.py
xlviews/utils.py
xlviews/xlviews.toml
xlviews-0.3.3.dist-info/WHEEL
xlviews-0.3.3.dist-info/METADATA
xlviews-0.3.3.dist-info/RECORD
