Metadata-Version: 2.3
Name: xlviews
Version: 0.3.3
Summary: DataFrames for Excel
Author: daizutabi
Author-email: daizutabi <daizutabi@gmail.com>
License: MIT License
Classifier: Development Status :: 4 - Beta
Classifier: Programming Language :: Python
Classifier: Programming Language :: Python :: 3.11
Classifier: Programming Language :: Python :: 3.12
Classifier: Programming Language :: Python :: 3.13
Classifier: Programming Language :: Python :: 3.14
Requires-Dist: numpy>=2
Requires-Dist: pandas>=2
Requires-Dist: xlwings>=0.33
Requires-Python: >=3.11
Project-URL: Documentation, https://github.com/daizutabi/xlviews
Project-URL: Issues, https://github.com/daizutabi/xlviews/issues
Project-URL: Source, https://github.com/daizutabi/xlviews
